LICENSE
MANIFEST.in
README.md
setup.py
libpython_heber.egg-info/PKG-INFO
libpython_heber.egg-info/SOURCES.txt
libpython_heber.egg-info/dependency_links.txt
libpython_heber.egg-info/not-zip-safe
libpython_heber.egg-info/requires.txt
libpython_heber.egg-info/top_level.txt
libpythonpro/__init__.py
libpythonpro/github_api.py